lightyear/__init__.py
lightyear/metrics/__init__.py
lightyear/metrics/bert_score.py
lightyear/metrics/bleu.py
lightyear/metrics/comet.py
lightyear-0.0.10.dist-info/LICENSE
lightyear-0.0.10.dist-info/METADATA
lightyear-0.0.10.dist-info/WHEEL
lightyear-0.0.10.dist-info/top_level.txt
lightyear-0.0.10.dist-info/RECORD
